SM16uout/SM16uout_data.py
SM16uout/__init__.py
sm16uout-1.0.3.dist-info/METADATA
sm16uout-1.0.3.dist-info/WHEEL
sm16uout-1.0.3.dist-info/top_level.txt
sm16uout-1.0.3.dist-info/RECORD
